{
  "generated_at_utc": "2026-06-01T00:06:14.086893+00:00",
  "next_cycle_utc": "2026-06-01T05:00:00+00:00",
  "cycle_close_utc": "2026-06-01T05:00:00+00:00",
  "minutes_to_expiry": 293.77,
  "binary_option_mode": true,
  "binary_option_horizon_minutes": 300,
  "top1": {
    "pair": "CADJPY",
    "name_ru": "Канад. доллар / Йена",
    "side": "BUY",
    "veto": null,
    "confidence": 93,
    "composite_score": 0.8139,
    "layers": {
      "technical": {
        "score": 23,
        "max_score": 34,
        "side": "BUY",
        "confidence": 91,
        "adx_h1": 37.4,
        "persistence_5h": 40.0,
        "multi_tf_aligned": true,
        "details": [
          {
            "name": "1D Тренд",
            "value": 3,
            "reason": "Сильный восходящий тренд (1D)"
          },
          {
            "name": "4H Тренд",
            "value": 1,
            "reason": "Умеренный рост (4H)"
          },
          {
            "name": "1H Тренд",
            "value": 2,
            "reason": "Подтверждён рост (1H)"
          },
          {
            "name": "15М Вход",
            "value": 1,
            "reason": "Цена выше EMA20 (15М)"
          },
          {
            "name": "RSI",
            "value": 2,
            "reason": "RSI 56 — бычья зона"
          },
          {
            "name": "MACD",
            "value": 3,
            "reason": "Пересечение MACD вверх — сильный бычий сигнал"
          },
          {
            "name": "Боллинджер",
            "value": 1,
            "reason": "Цена выше средней полосы"
          },
          {
            "name": "Стохастик",
            "value": 1,
            "reason": "K=77 > D=70 — бычий"
          },
          {
            "name": "ADX",
            "value": 3,
            "reason": "ADX 37 — сильный восходящий тренд"
          },
          {
            "name": "Ишимоку",
            "value": 3,
            "reason": "Выше облака + Tenkan > Kijun — сильный бычий"
          },
          {
            "name": "Моментум",
            "value": 1,
            "reason": "Моментум +0.06% — рост"
          },
          {
            "name": "Мульти-ТФ",
            "value": 3,
            "reason": "Все 4 таймфрейма бычьи (D1+H4+H1+M15)"
          },
          {
            "name": "Price Action",
            "value": -2,
            "reason": "Медвежье поглощение"
          },
          {
            "name": "EMA Кросс 15М",
            "value": 1,
            "reason": "EMA20 > EMA50 на 15М — бычий кросс"
          }
        ],
        "extras": {
          "smc": {
            "score": 0,
            "structure": {
              "event": "none",
              "score": 0,
              "last_high": 115.60099792480469,
              "last_low": 114.91400146484375,
              "trend": "down"
            },
            "sweep": {
              "event": "none",
              "score": 0
            },
            "order_blocks": [
              {
                "high": 115.19599914550781,
                "low": 114.91400146484375,
                "side": "bull",
                "index": 379
              },
              {
                "high": 115.18199920654297,
                "low": 115.0739974975586,
                "side": "bull",
                "index": 365
              },
              {
                "high": 115.40499877929688,
                "low": 115.28299713134766,
                "side": "bear",
                "index": 354
              },
              {
                "high": 116.03399658203125,
                "low": 115.7959976196289,
                "side": "bear",
                "index": 281
              },
              {
                "high": 117.45999908447266,
                "low": 117.18499755859375,
                "side": "bear",
                "index": 259
              }
            ],
            "fvgs": [
              {
                "top": 115.50700378417969,
                "bottom": 115.4520034790039,
                "side": "bear",
                "index": 384
              },
              {
                "top": 115.43800354003906,
                "bottom": 115.29100036621094,
                "side": "bull",
                "index": 381
              },
              {
                "top": 115.22200012207031,
                "bottom": 115.19599914550781,
                "side": "bull",
                "index": 380
              },
              {
                "top": 115.29100036621094,
                "bottom": 115.28399658203125,
                "side": "bear",
                "index": 356
              },
              {
                "top": 115.62999725341797,
                "bottom": 115.56400299072266,
                "side": "bear",
                "index": 341
              }
            ],
            "reasons": [
              "Свежий бычий order block",
              "Свежий медвежий FVG"
            ]
          },
          "wyckoff": {
            "phase": "range",
            "score": 0,
            "reason": "Боковой диапазон — без фазового перевеса"
          },
          "vp": {
            "poc": 115.272853,
            "vah": 115.516872,
            "val": 115.201083,
            "score": 0,
            "reason": "Цена внутри Value Area — равновесие"
          },
          "score": 0
        },
        "normalised": 0.947
      },
      "macro": {
        "score": 0,
        "base": -3.0,
        "quote": -3.0,
        "reason": "Макро: CAD нейтрально против JPY",
        "normalised": 0.0
      },
      "big_players": {
        "score": 2,
        "base": -0.34,
        "quote": -2.06,
        "reason": "Smart money сильно лонг CAD против JPY (base -0.34, quote -2.06)",
        "normalised": 0.667
      },
      "fundamental": {
        "score": 3,
        "reason": "Carry: CAD +2.75% vs JPY — сильный плюс",
        "normalised": 1.0
      },
      "news": {
        "score": 0,
        "reason": "Веток новостей нет",
        "next_event_base_min": 9999,
        "next_event_quote_min": 9999
      },
      "sentiment": {
        "score": 1,
        "reason": "Глобальный risk-on (DXY↓, VIX↓)",
        "normalised": 1.0
      },
      "political": {
        "score": 0,
        "reason": "Геополитика спокойна",
        "normalised": 0.0
      },
      "confluence": {
        "pair": "CADJPY",
        "side": "BUY",
        "score": 24,
        "max_score": 34,
        "score_pct": 0.706,
        "tf_directions": {
          "W1": 1,
          "D1": 1,
          "H4": 1,
          "H1": 1,
          "M15": 1
        },
        "tf_aligned": true,
        "votes": {
          "ema_stack": 1,
          "rsi": 1,
          "macd": 1,
          "stoch": 1,
          "adx": 1,
          "mfi": 1,
          "cci": 1,
          "obv": 0,
          "supertrend": -1,
          "vortex": 1
        },
        "bull_votes": 8,
        "bear_votes": 1,
        "neutral_votes": 1,
        "leading_count": 8,
        "adx_h1": 37.4,
        "squeeze_released": false,
        "squeeze_momentum_aligned": true,
        "super_confluence": true,
        "reasons": [
          "H1 EMA-стек бычий",
          "RSI(H1) 56 — в бычьей зоне",
          "MACD(H1) положителен",
          "ADX(H1) 37 с DI+ > DI- — тренд вверх",
          "MFI(H1) 62 — деньги входят (бычий)",
          "Supertrend(H1) медвежий"
        ],
        "normalised": 0.706,
        "bonus_applied": 0.18
      },
      "senior_alignment": {
        "weekly_aligned": true,
        "weekly_bias": "BUY",
        "m5_aligned": true,
        "reason": "W1 bias = BUY (согласован), M5 momentum согласован"
      },
      "safety_5h": {
        "passes": true,
        "reversal": {
          "reversal": false,
          "reason": "Разворотных паттернов нет",
          "bar_index": -1
        },
        "projection": {
          "passes": true,
          "reason": "Проекция на 4.9ч в плюсе: drift=+0.01710/ч, итог +0.08372 ≥ запас 0.07400",
          "projected_close": 115.58172,
          "entry": 115.498,
          "atr": 0.14957,
          "drift_per_bar": 0.0171,
          "drift_per_minute": 0.000285,
          "horizon_bars": 5,
          "horizon_minutes": 293.77,
          "safety_margin": 0.074
        }
      },
      "edge_check": {
        "passes": false,
        "calibrated_confidence": 71.4,
        "brain_confidence": 93,
        "reason": "Edge не подтверждён: 5d Wilson lower 39.0% < 51% (статистически не отличается от случайности); EV -0.76п. ≤ 0 (отрицательное матожидание на нижней границе WR).",
        "windows": {
          "5d": {
            "point_pct": 48.51,
            "lower_pct": 39.0,
            "upper_pct": 58.14,
            "wins": 49,
            "n": 101
          },
          "30d": {
            "point_pct": 53.28,
            "lower_pct": 48.26,
            "upper_pct": 58.23,
            "wins": 203,
            "n": 381
          },
          "lifetime": {
            "point_pct": 52.35,
            "lower_pct": 49.7,
            "upper_pct": 55.0,
            "wins": 712,
            "n": 1360
          }
        },
        "best_wilson": {
          "point_pct": 48.51,
          "lower_pct": 39.0,
          "upper_pct": 58.14,
          "wins": 49,
          "n": 101
        },
        "primary_window": "5d",
        "primary_floor_pct": 51.0,
        "mode": "standard",
        "expected_value_pp": -0.765,
        "wilson_lower_pct": 39.0,
        "lifetime_significant": false,
        "regime_ok": true,
        "lifetime_ok": true,
        "ev_positive": false,
        "calibrated_ok": true
      }
    },
    "levels": {
      "entry": 115.498,
      "stop_loss": 115.27364,
      "take_profit": 115.87193,
      "atr_h1": 0.14957,
      "rr_target": 1.66
    },
    "edge": {
      "passes": false,
      "calibrated_confidence": 71.4,
      "brain_confidence": 93,
      "reason": "Edge не подтверждён: 5d Wilson lower 39.0% < 51% (статистически не отличается от случайности); EV -0.76п. ≤ 0 (отрицательное матожидание на нижней границе WR).",
      "windows": {
        "5d": {
          "point_pct": 48.51,
          "lower_pct": 39.0,
          "upper_pct": 58.14,
          "wins": 49,
          "n": 101
        },
        "30d": {
          "point_pct": 53.28,
          "lower_pct": 48.26,
          "upper_pct": 58.23,
          "wins": 203,
          "n": 381
        },
        "lifetime": {
          "point_pct": 52.35,
          "lower_pct": 49.7,
          "upper_pct": 55.0,
          "wins": 712,
          "n": 1360
        }
      },
      "best_wilson": {
        "point_pct": 48.51,
        "lower_pct": 39.0,
        "upper_pct": 58.14,
        "wins": 49,
        "n": 101
      },
      "primary_window": "5d",
      "primary_floor_pct": 51.0,
      "mode": "standard",
      "expected_value_pp": -0.765,
      "wilson_lower_pct": 39.0,
      "lifetime_significant": false,
      "regime_ok": true,
      "lifetime_ok": true,
      "ev_positive": false,
      "calibrated_ok": true
    },
    "tier": "strong",
    "live_forecast": {
      "binary_option_mode": true,
      "horizon_minutes": 293.77,
      "entry": 115.498,
      "projected_close": 115.58172,
      "drift_per_hour": 0.0171,
      "drift_per_minute": 0.000285,
      "atr_h1": 0.14957,
      "safety_margin": 0.074,
      "stays_in_profit_at_expiry": true,
      "status_ru": "В ПЛЮСЕ",
      "reason": "Проекция на 4.9ч в плюсе: drift=+0.01710/ч, итог +0.08372 ≥ запас 0.07400"
    }
  },
  "top5": [
    {
      "pair": "CADJPY",
      "name_ru": "Канад. доллар / Йена",
      "side": "BUY",
      "veto": null,
      "confidence": 93,
      "composite_score": 0.8139,
      "layers": {
        "technical": {
          "score": 23,
          "max_score": 34,
          "side": "BUY",
          "confidence": 91,
          "adx_h1": 37.4,
          "persistence_5h": 40.0,
          "multi_tf_aligned": true,
          "details": [
            {
              "name": "1D Тренд",
              "value": 3,
              "reason": "Сильный восходящий тренд (1D)"
            },
            {
              "name": "4H Тренд",
              "value": 1,
              "reason": "Умеренный рост (4H)"
            },
            {
              "name": "1H Тренд",
              "value": 2,
              "reason": "Подтверждён рост (1H)"
            },
            {
              "name": "15М Вход",
              "value": 1,
              "reason": "Цена выше EMA20 (15М)"
            },
            {
              "name": "RSI",
              "value": 2,
              "reason": "RSI 56 — бычья зона"
            },
            {
              "name": "MACD",
              "value": 3,
              "reason": "Пересечение MACD вверх — сильный бычий сигнал"
            },
            {
              "name": "Боллинджер",
              "value": 1,
              "reason": "Цена выше средней полосы"
            },
            {
              "name": "Стохастик",
              "value": 1,
              "reason": "K=77 > D=70 — бычий"
            },
            {
              "name": "ADX",
              "value": 3,
              "reason": "ADX 37 — сильный восходящий тренд"
            },
            {
              "name": "Ишимоку",
              "value": 3,
              "reason": "Выше облака + Tenkan > Kijun — сильный бычий"
            },
            {
              "name": "Моментум",
              "value": 1,
              "reason": "Моментум +0.06% — рост"
            },
            {
              "name": "Мульти-ТФ",
              "value": 3,
              "reason": "Все 4 таймфрейма бычьи (D1+H4+H1+M15)"
            },
            {
              "name": "Price Action",
              "value": -2,
              "reason": "Медвежье поглощение"
            },
            {
              "name": "EMA Кросс 15М",
              "value": 1,
              "reason": "EMA20 > EMA50 на 15М — бычий кросс"
            }
          ],
          "extras": {
            "smc": {
              "score": 0,
              "structure": {
                "event": "none",
                "score": 0,
                "last_high": 115.60099792480469,
                "last_low": 114.91400146484375,
                "trend": "down"
              },
              "sweep": {
                "event": "none",
                "score": 0
              },
              "order_blocks": [
                {
                  "high": 115.19599914550781,
                  "low": 114.91400146484375,
                  "side": "bull",
                  "index": 379
                },
                {
                  "high": 115.18199920654297,
                  "low": 115.0739974975586,
                  "side": "bull",
                  "index": 365
                },
                {
                  "high": 115.40499877929688,
                  "low": 115.28299713134766,
                  "side": "bear",
                  "index": 354
                },
                {
                  "high": 116.03399658203125,
                  "low": 115.7959976196289,
                  "side": "bear",
                  "index": 281
                },
                {
                  "high": 117.45999908447266,
                  "low": 117.18499755859375,
                  "side": "bear",
                  "index": 259
                }
              ],
              "fvgs": [
                {
                  "top": 115.50700378417969,
                  "bottom": 115.4520034790039,
                  "side": "bear",
                  "index": 384
                },
                {
                  "top": 115.43800354003906,
                  "bottom": 115.29100036621094,
                  "side": "bull",
                  "index": 381
                },
                {
                  "top": 115.22200012207031,
                  "bottom": 115.19599914550781,
                  "side": "bull",
                  "index": 380
                },
                {
                  "top": 115.29100036621094,
                  "bottom": 115.28399658203125,
                  "side": "bear",
                  "index": 356
                },
                {
                  "top": 115.62999725341797,
                  "bottom": 115.56400299072266,
                  "side": "bear",
                  "index": 341
                }
              ],
              "reasons": [
                "Свежий бычий order block",
                "Свежий медвежий FVG"
              ]
            },
            "wyckoff": {
              "phase": "range",
              "score": 0,
              "reason": "Боковой диапазон — без фазового перевеса"
            },
            "vp": {
              "poc": 115.272853,
              "vah": 115.516872,
              "val": 115.201083,
              "score": 0,
              "reason": "Цена внутри Value Area — равновесие"
            },
            "score": 0
          },
          "normalised": 0.947
        },
        "macro": {
          "score": 0,
          "base": -3.0,
          "quote": -3.0,
          "reason": "Макро: CAD нейтрально против JPY",
          "normalised": 0.0
        },
        "big_players": {
          "score": 2,
          "base": -0.34,
          "quote": -2.06,
          "reason": "Smart money сильно лонг CAD против JPY (base -0.34, quote -2.06)",
          "normalised": 0.667
        },
        "fundamental": {
          "score": 3,
          "reason": "Carry: CAD +2.75% vs JPY — сильный плюс",
          "normalised": 1.0
        },
        "news": {
          "score": 0,
          "reason": "Веток новостей нет",
          "next_event_base_min": 9999,
          "next_event_quote_min": 9999
        },
        "sentiment": {
          "score": 1,
          "reason": "Глобальный risk-on (DXY↓, VIX↓)",
          "normalised": 1.0
        },
        "political": {
          "score": 0,
          "reason": "Геополитика спокойна",
          "normalised": 0.0
        },
        "confluence": {
          "pair": "CADJPY",
          "side": "BUY",
          "score": 24,
          "max_score": 34,
          "score_pct": 0.706,
          "tf_directions": {
            "W1": 1,
            "D1": 1,
            "H4": 1,
            "H1": 1,
            "M15": 1
          },
          "tf_aligned": true,
          "votes": {
            "ema_stack": 1,
            "rsi": 1,
            "macd": 1,
            "stoch": 1,
            "adx": 1,
            "mfi": 1,
            "cci": 1,
            "obv": 0,
            "supertrend": -1,
            "vortex": 1
          },
          "bull_votes": 8,
          "bear_votes": 1,
          "neutral_votes": 1,
          "leading_count": 8,
          "adx_h1": 37.4,
          "squeeze_released": false,
          "squeeze_momentum_aligned": true,
          "super_confluence": true,
          "reasons": [
            "H1 EMA-стек бычий",
            "RSI(H1) 56 — в бычьей зоне",
            "MACD(H1) положителен",
            "ADX(H1) 37 с DI+ > DI- — тренд вверх",
            "MFI(H1) 62 — деньги входят (бычий)",
            "Supertrend(H1) медвежий"
          ],
          "normalised": 0.706,
          "bonus_applied": 0.18
        },
        "senior_alignment": {
          "weekly_aligned": true,
          "weekly_bias": "BUY",
          "m5_aligned": true,
          "reason": "W1 bias = BUY (согласован), M5 momentum согласован"
        },
        "safety_5h": {
          "passes": true,
          "reversal": {
            "reversal": false,
            "reason": "Разворотных паттернов нет",
            "bar_index": -1
          },
          "projection": {
            "passes": true,
            "reason": "Проекция на 4.9ч в плюсе: drift=+0.01710/ч, итог +0.08372 ≥ запас 0.07400",
            "projected_close": 115.58172,
            "entry": 115.498,
            "atr": 0.14957,
            "drift_per_bar": 0.0171,
            "drift_per_minute": 0.000285,
            "horizon_bars": 5,
            "horizon_minutes": 293.77,
            "safety_margin": 0.074
          }
        },
        "edge_check": {
          "passes": false,
          "calibrated_confidence": 71.4,
          "brain_confidence": 93,
          "reason": "Edge не подтверждён: 5d Wilson lower 39.0% < 51% (статистически не отличается от случайности); EV -0.76п. ≤ 0 (отрицательное матожидание на нижней границе WR).",
          "windows": {
            "5d": {
              "point_pct": 48.51,
              "lower_pct": 39.0,
              "upper_pct": 58.14,
              "wins": 49,
              "n": 101
            },
            "30d": {
              "point_pct": 53.28,
              "lower_pct": 48.26,
              "upper_pct": 58.23,
              "wins": 203,
              "n": 381
            },
            "lifetime": {
              "point_pct": 52.35,
              "lower_pct": 49.7,
              "upper_pct": 55.0,
              "wins": 712,
              "n": 1360
            }
          },
          "best_wilson": {
            "point_pct": 48.51,
            "lower_pct": 39.0,
            "upper_pct": 58.14,
            "wins": 49,
            "n": 101
          },
          "primary_window": "5d",
          "primary_floor_pct": 51.0,
          "mode": "standard",
          "expected_value_pp": -0.765,
          "wilson_lower_pct": 39.0,
          "lifetime_significant": false,
          "regime_ok": true,
          "lifetime_ok": true,
          "ev_positive": false,
          "calibrated_ok": true
        }
      },
      "levels": {
        "entry": 115.498,
        "stop_loss": 115.27364,
        "take_profit": 115.87193,
        "atr_h1": 0.14957,
        "rr_target": 1.66
      }
    }
  ],
  "live_forecast": {
    "binary_option_mode": true,
    "horizon_minutes": 293.77,
    "entry": 115.498,
    "projected_close": 115.58172,
    "drift_per_hour": 0.0171,
    "drift_per_minute": 0.000285,
    "atr_h1": 0.14957,
    "safety_margin": 0.074,
    "stays_in_profit_at_expiry": true,
    "status_ru": "В ПЛЮСЕ",
    "reason": "Проекция на 4.9ч в плюсе: drift=+0.01710/ч, итог +0.08372 ≥ запас 0.07400"
  },
  "leading_candidate": {
    "pair": "CADJPY",
    "name_ru": "Канад. доллар / Йена",
    "side": "BUY",
    "confidence": 93,
    "veto": null,
    "composite_score": 0.8139
  },
  "macro_currency_strength": {
    "USD": -1.83,
    "EUR": 2.08,
    "GBP": -1.54,
    "JPY": -3.0,
    "CHF": 1.62,
    "AUD": -3.0,
    "CAD": -3.0,
    "NZD": -3.0
  },
  "sentiment": {
    "score": 1,
    "reason": "Глобальный risk-on (DXY↓, VIX↓)"
  },
  "political_risk": {
    "USD": 0,
    "EUR": 0,
    "GBP": 0,
    "JPY": 0,
    "CHF": 0,
    "AUD": 0,
    "CAD": 0,
    "NZD": 0
  },
  "big_players": {
    "currency_scores": {
      "USD": -0.12,
      "EUR": -0.08,
      "GBP": -0.56,
      "JPY": -2.06,
      "CHF": 0.54,
      "AUD": 0.7,
      "CAD": -0.34,
      "NZD": -0.29
    },
    "components": {
      "cot": {
        "USD": 1.21,
        "EUR": -1.62,
        "GBP": -0.86,
        "JPY": -1.95,
        "CHF": -0.43,
        "AUD": 1.31,
        "CAD": 0.03,
        "NZD": -0.31
      },
      "orderbook": {
        "USD": -2.38,
        "EUR": 2.38,
        "GBP": 1.32,
        "JPY": -1.44,
        "CHF": 2.37,
        "AUD": 2.56,
        "CAD": 1.19,
        "NZD": 2.5
      },
      "macro": {
        "USD": -1.83,
        "EUR": 2.08,
        "GBP": -1.54,
        "JPY": -3.0,
        "CHF": 1.62,
        "AUD": -3.0,
        "CAD": -3.0,
        "NZD": -3.0
      }
    }
  },
  "favorite_check": {
    "ok": false,
    "tier": "strong",
    "reason": "⚡ STRONG: brain 93% ≥ 80%, но мат. преимущество на дистанции пока не подтверждено: Edge не подтверждён: 5d Wilson lower 39.0% < 51% (статистически не отличается от случайности); EV -0.76п. ≤ 0 (отрицательное матожидание на нижней границе WR).",
    "lead_required": 5,
    "confidence_floor": 80,
    "edge_check": {
      "passes": false,
      "calibrated_confidence": 71.4,
      "brain_confidence": 93,
      "reason": "Edge не подтверждён: 5d Wilson lower 39.0% < 51% (статистически не отличается от случайности); EV -0.76п. ≤ 0 (отрицательное матожидание на нижней границе WR).",
      "windows": {
        "5d": {
          "point_pct": 48.51,
          "lower_pct": 39.0,
          "upper_pct": 58.14,
          "wins": 49,
          "n": 101
        },
        "30d": {
          "point_pct": 53.28,
          "lower_pct": 48.26,
          "upper_pct": 58.23,
          "wins": 203,
          "n": 381
        },
        "lifetime": {
          "point_pct": 52.35,
          "lower_pct": 49.7,
          "upper_pct": 55.0,
          "wins": 712,
          "n": 1360
        }
      },
      "best_wilson": {
        "point_pct": 48.51,
        "lower_pct": 39.0,
        "upper_pct": 58.14,
        "wins": 49,
        "n": 101
      },
      "primary_window": "5d",
      "primary_floor_pct": 51.0,
      "mode": "standard",
      "expected_value_pp": -0.765,
      "wilson_lower_pct": 39.0,
      "lifetime_significant": false,
      "regime_ok": true,
      "lifetime_ok": true,
      "ev_positive": false,
      "calibrated_ok": true
    },
    "wilson_lifetime_floor_pct": 51,
    "wilson_regime_floor_pct": 45
  }
}