{
  "generated_at_utc": "2026-05-26T20:50:23.252520+00:00",
  "next_cycle_utc": "2026-05-27T00:00:00+00:00",
  "cycle_close_utc": "2026-05-27T00:00:00+00:00",
  "minutes_to_expiry": 189.61,
  "binary_option_mode": true,
  "binary_option_horizon_minutes": 300,
  "top1": {
    "pair": "GBPAUD",
    "name_ru": "Фунт / Австрал. доллар",
    "side": "SELL",
    "veto": null,
    "confidence": 62,
    "composite_score": 0.301,
    "layers": {
      "technical": {
        "score": -19,
        "max_score": 34,
        "side": "SELL",
        "confidence": 89,
        "adx_h1": 54.3,
        "persistence_5h": 20.0,
        "multi_tf_aligned": true,
        "details": [
          {
            "name": "1D Тренд",
            "value": -3,
            "reason": "Сильный нисходящий тренд (1D)"
          },
          {
            "name": "4H Тренд",
            "value": -3,
            "reason": "Сильный нисходящий тренд (4H)"
          },
          {
            "name": "1H Тренд",
            "value": -2,
            "reason": "Подтверждено падение (1H)"
          },
          {
            "name": "15М Вход",
            "value": -1,
            "reason": "Цена ниже EMA20 (15М)"
          },
          {
            "name": "RSI",
            "value": 3,
            "reason": "RSI 26 — перепроданность, ожидается отскок"
          },
          {
            "name": "MACD",
            "value": -1,
            "reason": "MACD отрицательный"
          },
          {
            "name": "Боллинджер",
            "value": -1,
            "reason": "Цена ниже средней полосы"
          },
          {
            "name": "Стохастик",
            "value": 2,
            "reason": "K=15 D=9 — перепроданность"
          },
          {
            "name": "ADX",
            "value": -3,
            "reason": "ADX 54 — сильный нисходящий тренд"
          },
          {
            "name": "Williams %R",
            "value": 1,
            "reason": "W%R -85 — перепроданность"
          },
          {
            "name": "Ишимоку",
            "value": -3,
            "reason": "Ниже облака + Tenkan < Kijun — сильный медвежий"
          },
          {
            "name": "VWAP",
            "value": -1,
            "reason": "Цена ниже VWAP — медвежий настрой"
          },
          {
            "name": "Мульти-ТФ",
            "value": -3,
            "reason": "Все 4 таймфрейма медвежьи (D1+H4+H1+M15)"
          },
          {
            "name": "Price Action",
            "value": -3,
            "reason": "Пин-бар (медвежий); Медвежье поглощение"
          },
          {
            "name": "EMA Кросс 15М",
            "value": -1,
            "reason": "EMA20 < EMA50 на 15М — медвежий кросс"
          }
        ],
        "extras": {
          "smc": {
            "score": -4,
            "structure": {
              "event": "choch_down",
              "score": -2,
              "last_high": 1.8834400177001953,
              "last_low": 1.8795700073242188,
              "trend": "range"
            },
            "sweep": {
              "event": "none",
              "score": 0
            },
            "order_blocks": [
              {
                "high": 1.8823599815368652,
                "low": 1.87978994846344,
                "side": "bear",
                "index": 374
              },
              {
                "high": 1.8880499601364136,
                "low": 1.8840899467468262,
                "side": "bear",
                "index": 348
              },
              {
                "high": 1.8816699981689453,
                "low": 1.8778400421142578,
                "side": "bull",
                "index": 343
              },
              {
                "high": 1.8692100048065186,
                "low": 1.8657900094985962,
                "side": "bull",
                "index": 338
              },
              {
                "high": 1.8567700386047363,
                "low": 1.8533600568771362,
                "side": "bull",
                "index": 329
              }
            ],
            "fvgs": [
              {
                "top": 1.87978994846344,
                "bottom": 1.8771799802780151,
                "side": "bear",
                "index": 375
              },
              {
                "top": 1.882099986076355,
                "bottom": 1.8807599544525146,
                "side": "bear",
                "index": 357
              },
              {
                "top": 1.8838000297546387,
                "bottom": 1.8791899681091309,
                "side": "bull",
                "index": 354
              },
              {
                "top": 1.882889986038208,
                "bottom": 1.8818000555038452,
                "side": "bear",
                "index": 350
              },
              {
                "top": 1.8824199438095093,
                "bottom": 1.8816699981689453,
                "side": "bull",
                "index": 344
              }
            ],
            "reasons": [
              "Смена характера вниз (CHoCH)",
              "Свежий медвежий order block",
              "Свежий медвежий FVG"
            ]
          },
          "wyckoff": {
            "phase": "distribution",
            "score": -2,
            "reason": "Сжатие в верхней трети диапазона — распределение",
            "volume_contraction": false
          },
          "vp": {
            "poc": 1.881532,
            "vah": 1.88497,
            "val": 1.878095,
            "score": -1,
            "reason": "Цена ниже Value Area Low — институциональное предложение"
          },
          "score": -7
        },
        "normalised": -1.0
      },
      "macro": {
        "score": 3,
        "base": 3.0,
        "quote": -3.0,
        "reason": "Макро: GBP укрепляется против AUD",
        "normalised": 1.0
      },
      "big_players": {
        "score": -1,
        "base": 0.1,
        "quote": 0.86,
        "reason": "Smart money умеренно шорт GBP против AUD (base +0.10, quote +0.86)",
        "normalised": -0.333
      },
      "fundamental": {
        "score": 1,
        "reason": "Carry: GBP +0.65% vs AUD",
        "normalised": 0.333
      },
      "news": {
        "score": 0,
        "reason": "Веток новостей нет",
        "next_event_base_min": 3569,
        "next_event_quote_min": 279
      },
      "sentiment": {
        "score": 0,
        "reason": "Sentiment без выраженного перевеса",
        "normalised": 0.0
      },
      "political": {
        "score": 0,
        "reason": "Геополитика спокойна",
        "normalised": 0.0
      },
      "confluence": {
        "pair": "GBPAUD",
        "side": "SELL",
        "score": -16,
        "max_score": 34,
        "score_pct": 0.471,
        "tf_directions": {
          "W1": -1,
          "D1": -1,
          "H4": 0,
          "H1": -1,
          "M15": -1
        },
        "tf_aligned": false,
        "votes": {
          "ema_stack": -1,
          "rsi": -1,
          "macd": -1,
          "stoch": 1,
          "adx": -1,
          "mfi": -1,
          "cci": -1,
          "obv": -1,
          "supertrend": -1,
          "vortex": -1
        },
        "bull_votes": 1,
        "bear_votes": 9,
        "neutral_votes": 0,
        "leading_count": 9,
        "adx_h1": 54.3,
        "squeeze_released": false,
        "squeeze_momentum_aligned": true,
        "super_confluence": false,
        "reasons": [
          "H1 EMA-стек медвежий",
          "RSI(H1) 26 — в медвежьей зоне",
          "MACD(H1) отрицателен",
          "ADX(H1) 54 с DI- > DI+ — тренд вниз",
          "MFI(H1) 21 — деньги выходят (медвежий)",
          "CCI(H1) -101 — сильный медвежий импульс"
        ],
        "normalised": -0.471,
        "bonus_applied": 0.0
      },
      "senior_alignment": {
        "weekly_aligned": true,
        "weekly_bias": "SELL",
        "m5_aligned": true,
        "reason": "W1 bias = SELL (согласован), M5 momentum согласован"
      },
      "safety_5h": {
        "passes": true,
        "reversal": {
          "reversal": false,
          "reason": "Разворотных паттернов нет",
          "bar_index": -1
        },
        "projection": {
          "passes": true,
          "reason": "Проекция на 3.2ч в плюсе: drift=-0.00053/ч, итог +0.00166 ≥ запас 0.00066",
          "projected_close": 1.87472,
          "entry": 1.87638,
          "atr": 0.00166,
          "drift_per_bar": -0.00053,
          "drift_per_minute": -8.8e-06,
          "horizon_bars": 5,
          "horizon_minutes": 189.61,
          "safety_margin": 0.00066
        }
      },
      "edge_check": {
        "passes": false,
        "calibrated_confidence": 48.5,
        "brain_confidence": 62,
        "reason": "Edge не подтверждён: 5d Wilson lower 28.2% < 51% (статистически не отличается от случайности); EV -6.67п. ≤ 0 (отрицательное матожидание на нижней границе WR).",
        "windows": {
          "5d": {
            "point_pct": 40.38,
            "lower_pct": 28.16,
            "upper_pct": 53.93,
            "wins": 21,
            "n": 52
          },
          "30d": {
            "point_pct": 50.9,
            "lower_pct": 46.94,
            "upper_pct": 54.85,
            "wins": 311,
            "n": 611
          },
          "lifetime": {
            "point_pct": 53.59,
            "lower_pct": 51.08,
            "upper_pct": 56.07,
            "wins": 822,
            "n": 1534
          }
        },
        "best_wilson": {
          "point_pct": 40.38,
          "lower_pct": 28.16,
          "upper_pct": 53.93,
          "wins": 21,
          "n": 52
        },
        "primary_window": "5d",
        "primary_floor_pct": 51.0,
        "mode": "standard",
        "expected_value_pp": -6.667,
        "wilson_lower_pct": 28.16,
        "lifetime_significant": false,
        "regime_ok": true,
        "lifetime_ok": true,
        "ev_positive": false,
        "calibrated_ok": true
      }
    },
    "levels": {
      "entry": 1.87638,
      "stop_loss": 1.87887,
      "take_profit": 1.87223,
      "atr_h1": 0.00166,
      "rr_target": 1.66
    },
    "edge": {
      "passes": false,
      "calibrated_confidence": 48.5,
      "brain_confidence": 62,
      "reason": "Edge не подтверждён: 5d Wilson lower 28.2% < 51% (статистически не отличается от случайности); EV -6.67п. ≤ 0 (отрицательное матожидание на нижней границе WR).",
      "windows": {
        "5d": {
          "point_pct": 40.38,
          "lower_pct": 28.16,
          "upper_pct": 53.93,
          "wins": 21,
          "n": 52
        },
        "30d": {
          "point_pct": 50.9,
          "lower_pct": 46.94,
          "upper_pct": 54.85,
          "wins": 311,
          "n": 611
        },
        "lifetime": {
          "point_pct": 53.59,
          "lower_pct": 51.08,
          "upper_pct": 56.07,
          "wins": 822,
          "n": 1534
        }
      },
      "best_wilson": {
        "point_pct": 40.38,
        "lower_pct": 28.16,
        "upper_pct": 53.93,
        "wins": 21,
        "n": 52
      },
      "primary_window": "5d",
      "primary_floor_pct": 51.0,
      "mode": "standard",
      "expected_value_pp": -6.667,
      "wilson_lower_pct": 28.16,
      "lifetime_significant": false,
      "regime_ok": true,
      "lifetime_ok": true,
      "ev_positive": false,
      "calibrated_ok": true
    },
    "tier": "normal",
    "live_forecast": {
      "binary_option_mode": true,
      "horizon_minutes": 189.61,
      "entry": 1.87638,
      "projected_close": 1.87472,
      "drift_per_hour": -0.00053,
      "drift_per_minute": -8.8e-06,
      "atr_h1": 0.00166,
      "safety_margin": 0.00066,
      "stays_in_profit_at_expiry": true,
      "status_ru": "В ПЛЮСЕ",
      "reason": "Проекция на 3.2ч в плюсе: drift=-0.00053/ч, итог +0.00166 ≥ запас 0.00066"
    }
  },
  "top5": [
    {
      "pair": "GBPAUD",
      "name_ru": "Фунт / Австрал. доллар",
      "side": "SELL",
      "veto": null,
      "confidence": 62,
      "composite_score": 0.301,
      "layers": {
        "technical": {
          "score": -19,
          "max_score": 34,
          "side": "SELL",
          "confidence": 89,
          "adx_h1": 54.3,
          "persistence_5h": 20.0,
          "multi_tf_aligned": true,
          "details": [
            {
              "name": "1D Тренд",
              "value": -3,
              "reason": "Сильный нисходящий тренд (1D)"
            },
            {
              "name": "4H Тренд",
              "value": -3,
              "reason": "Сильный нисходящий тренд (4H)"
            },
            {
              "name": "1H Тренд",
              "value": -2,
              "reason": "Подтверждено падение (1H)"
            },
            {
              "name": "15М Вход",
              "value": -1,
              "reason": "Цена ниже EMA20 (15М)"
            },
            {
              "name": "RSI",
              "value": 3,
              "reason": "RSI 26 — перепроданность, ожидается отскок"
            },
            {
              "name": "MACD",
              "value": -1,
              "reason": "MACD отрицательный"
            },
            {
              "name": "Боллинджер",
              "value": -1,
              "reason": "Цена ниже средней полосы"
            },
            {
              "name": "Стохастик",
              "value": 2,
              "reason": "K=15 D=9 — перепроданность"
            },
            {
              "name": "ADX",
              "value": -3,
              "reason": "ADX 54 — сильный нисходящий тренд"
            },
            {
              "name": "Williams %R",
              "value": 1,
              "reason": "W%R -85 — перепроданность"
            },
            {
              "name": "Ишимоку",
              "value": -3,
              "reason": "Ниже облака + Tenkan < Kijun — сильный медвежий"
            },
            {
              "name": "VWAP",
              "value": -1,
              "reason": "Цена ниже VWAP — медвежий настрой"
            },
            {
              "name": "Мульти-ТФ",
              "value": -3,
              "reason": "Все 4 таймфрейма медвежьи (D1+H4+H1+M15)"
            },
            {
              "name": "Price Action",
              "value": -3,
              "reason": "Пин-бар (медвежий); Медвежье поглощение"
            },
            {
              "name": "EMA Кросс 15М",
              "value": -1,
              "reason": "EMA20 < EMA50 на 15М — медвежий кросс"
            }
          ],
          "extras": {
            "smc": {
              "score": -4,
              "structure": {
                "event": "choch_down",
                "score": -2,
                "last_high": 1.8834400177001953,
                "last_low": 1.8795700073242188,
                "trend": "range"
              },
              "sweep": {
                "event": "none",
                "score": 0
              },
              "order_blocks": [
                {
                  "high": 1.8823599815368652,
                  "low": 1.87978994846344,
                  "side": "bear",
                  "index": 374
                },
                {
                  "high": 1.8880499601364136,
                  "low": 1.8840899467468262,
                  "side": "bear",
                  "index": 348
                },
                {
                  "high": 1.8816699981689453,
                  "low": 1.8778400421142578,
                  "side": "bull",
                  "index": 343
                },
                {
                  "high": 1.8692100048065186,
                  "low": 1.8657900094985962,
                  "side": "bull",
                  "index": 338
                },
                {
                  "high": 1.8567700386047363,
                  "low": 1.8533600568771362,
                  "side": "bull",
                  "index": 329
                }
              ],
              "fvgs": [
                {
                  "top": 1.87978994846344,
                  "bottom": 1.8771799802780151,
                  "side": "bear",
                  "index": 375
                },
                {
                  "top": 1.882099986076355,
                  "bottom": 1.8807599544525146,
                  "side": "bear",
                  "index": 357
                },
                {
                  "top": 1.8838000297546387,
                  "bottom": 1.8791899681091309,
                  "side": "bull",
                  "index": 354
                },
                {
                  "top": 1.882889986038208,
                  "bottom": 1.8818000555038452,
                  "side": "bear",
                  "index": 350
                },
                {
                  "top": 1.8824199438095093,
                  "bottom": 1.8816699981689453,
                  "side": "bull",
                  "index": 344
                }
              ],
              "reasons": [
                "Смена характера вниз (CHoCH)",
                "Свежий медвежий order block",
                "Свежий медвежий FVG"
              ]
            },
            "wyckoff": {
              "phase": "distribution",
              "score": -2,
              "reason": "Сжатие в верхней трети диапазона — распределение",
              "volume_contraction": false
            },
            "vp": {
              "poc": 1.881532,
              "vah": 1.88497,
              "val": 1.878095,
              "score": -1,
              "reason": "Цена ниже Value Area Low — институциональное предложение"
            },
            "score": -7
          },
          "normalised": -1.0
        },
        "macro": {
          "score": 3,
          "base": 3.0,
          "quote": -3.0,
          "reason": "Макро: GBP укрепляется против AUD",
          "normalised": 1.0
        },
        "big_players": {
          "score": -1,
          "base": 0.1,
          "quote": 0.86,
          "reason": "Smart money умеренно шорт GBP против AUD (base +0.10, quote +0.86)",
          "normalised": -0.333
        },
        "fundamental": {
          "score": 1,
          "reason": "Carry: GBP +0.65% vs AUD",
          "normalised": 0.333
        },
        "news": {
          "score": 0,
          "reason": "Веток новостей нет",
          "next_event_base_min": 3569,
          "next_event_quote_min": 279
        },
        "sentiment": {
          "score": 0,
          "reason": "Sentiment без выраженного перевеса",
          "normalised": 0.0
        },
        "political": {
          "score": 0,
          "reason": "Геополитика спокойна",
          "normalised": 0.0
        },
        "confluence": {
          "pair": "GBPAUD",
          "side": "SELL",
          "score": -16,
          "max_score": 34,
          "score_pct": 0.471,
          "tf_directions": {
            "W1": -1,
            "D1": -1,
            "H4": 0,
            "H1": -1,
            "M15": -1
          },
          "tf_aligned": false,
          "votes": {
            "ema_stack": -1,
            "rsi": -1,
            "macd": -1,
            "stoch": 1,
            "adx": -1,
            "mfi": -1,
            "cci": -1,
            "obv": -1,
            "supertrend": -1,
            "vortex": -1
          },
          "bull_votes": 1,
          "bear_votes": 9,
          "neutral_votes": 0,
          "leading_count": 9,
          "adx_h1": 54.3,
          "squeeze_released": false,
          "squeeze_momentum_aligned": true,
          "super_confluence": false,
          "reasons": [
            "H1 EMA-стек медвежий",
            "RSI(H1) 26 — в медвежьей зоне",
            "MACD(H1) отрицателен",
            "ADX(H1) 54 с DI- > DI+ — тренд вниз",
            "MFI(H1) 21 — деньги выходят (медвежий)",
            "CCI(H1) -101 — сильный медвежий импульс"
          ],
          "normalised": -0.471,
          "bonus_applied": 0.0
        },
        "senior_alignment": {
          "weekly_aligned": true,
          "weekly_bias": "SELL",
          "m5_aligned": true,
          "reason": "W1 bias = SELL (согласован), M5 momentum согласован"
        },
        "safety_5h": {
          "passes": true,
          "reversal": {
            "reversal": false,
            "reason": "Разворотных паттернов нет",
            "bar_index": -1
          },
          "projection": {
            "passes": true,
            "reason": "Проекция на 3.2ч в плюсе: drift=-0.00053/ч, итог +0.00166 ≥ запас 0.00066",
            "projected_close": 1.87472,
            "entry": 1.87638,
            "atr": 0.00166,
            "drift_per_bar": -0.00053,
            "drift_per_minute": -8.8e-06,
            "horizon_bars": 5,
            "horizon_minutes": 189.61,
            "safety_margin": 0.00066
          }
        },
        "edge_check": {
          "passes": false,
          "calibrated_confidence": 48.5,
          "brain_confidence": 62,
          "reason": "Edge не подтверждён: 5d Wilson lower 28.2% < 51% (статистически не отличается от случайности); EV -6.67п. ≤ 0 (отрицательное матожидание на нижней границе WR).",
          "windows": {
            "5d": {
              "point_pct": 40.38,
              "lower_pct": 28.16,
              "upper_pct": 53.93,
              "wins": 21,
              "n": 52
            },
            "30d": {
              "point_pct": 50.9,
              "lower_pct": 46.94,
              "upper_pct": 54.85,
              "wins": 311,
              "n": 611
            },
            "lifetime": {
              "point_pct": 53.59,
              "lower_pct": 51.08,
              "upper_pct": 56.07,
              "wins": 822,
              "n": 1534
            }
          },
          "best_wilson": {
            "point_pct": 40.38,
            "lower_pct": 28.16,
            "upper_pct": 53.93,
            "wins": 21,
            "n": 52
          },
          "primary_window": "5d",
          "primary_floor_pct": 51.0,
          "mode": "standard",
          "expected_value_pp": -6.667,
          "wilson_lower_pct": 28.16,
          "lifetime_significant": false,
          "regime_ok": true,
          "lifetime_ok": true,
          "ev_positive": false,
          "calibrated_ok": true
        }
      },
      "levels": {
        "entry": 1.87638,
        "stop_loss": 1.87887,
        "take_profit": 1.87223,
        "atr_h1": 0.00166,
        "rr_target": 1.66
      }
    }
  ],
  "live_forecast": {
    "binary_option_mode": true,
    "horizon_minutes": 189.61,
    "entry": 1.87638,
    "projected_close": 1.87472,
    "drift_per_hour": -0.00053,
    "drift_per_minute": -8.8e-06,
    "atr_h1": 0.00166,
    "safety_margin": 0.00066,
    "stays_in_profit_at_expiry": true,
    "status_ru": "В ПЛЮСЕ",
    "reason": "Проекция на 3.2ч в плюсе: drift=-0.00053/ч, итог +0.00166 ≥ запас 0.00066"
  },
  "leading_candidate": {
    "pair": "GBPAUD",
    "name_ru": "Фунт / Австрал. доллар",
    "side": "SELL",
    "confidence": 62,
    "veto": null,
    "composite_score": 0.301
  },
  "macro_currency_strength": {
    "USD": 1.34,
    "EUR": 3.0,
    "GBP": 3.0,
    "JPY": -1.46,
    "CHF": -1.28,
    "AUD": -3.0,
    "CAD": -3.0,
    "NZD": -3.0
  },
  "sentiment": {
    "score": 0,
    "reason": "Sentiment без выраженного перевеса"
  },
  "political_risk": {
    "USD": 0,
    "EUR": 0,
    "GBP": 0,
    "JPY": 0,
    "CHF": 0,
    "AUD": 0,
    "CAD": 0,
    "NZD": 0
  },
  "big_players": {
    "currency_scores": {
      "USD": 0.82,
      "EUR": -0.16,
      "GBP": 0.1,
      "JPY": -1.85,
      "CHF": -0.63,
      "AUD": 0.86,
      "CAD": -0.49,
      "NZD": -1.57
    },
    "components": {
      "cot": {
        "USD": 1.24,
        "EUR": -1.58,
        "GBP": -0.97,
        "JPY": -1.72,
        "CHF": -0.71,
        "AUD": 1.81,
        "CAD": 0.75,
        "NZD": -0.68
      },
      "orderbook": {
        "USD": -0.94,
        "EUR": 0.94,
        "GBP": 0.39,
        "JPY": -2.64,
        "CHF": 0.27,
        "AUD": 1.85,
        "CAD": -1.72,
        "NZD": -2.82
      },
      "macro": {
        "USD": 1.34,
        "EUR": 3.0,
        "GBP": 3.0,
        "JPY": -1.46,
        "CHF": -1.28,
        "AUD": -3.0,
        "CAD": -3.0,
        "NZD": -3.0
      }
    }
  },
  "favorite_check": {
    "ok": false,
    "tier": "normal",
    "reason": "⊙ NORMAL: лидер GBPAUD brain 62% < порог 80% — сигнал слабый, торговать только если согласен с уровнем уверенности (Top-2 0%, отрыв 62 п.)",
    "lead_required": 5,
    "confidence_floor": 80,
    "edge_check": {
      "passes": false,
      "calibrated_confidence": 48.5,
      "brain_confidence": 62,
      "reason": "Edge не подтверждён: 5d Wilson lower 28.2% < 51% (статистически не отличается от случайности); EV -6.67п. ≤ 0 (отрицательное матожидание на нижней границе WR).",
      "windows": {
        "5d": {
          "point_pct": 40.38,
          "lower_pct": 28.16,
          "upper_pct": 53.93,
          "wins": 21,
          "n": 52
        },
        "30d": {
          "point_pct": 50.9,
          "lower_pct": 46.94,
          "upper_pct": 54.85,
          "wins": 311,
          "n": 611
        },
        "lifetime": {
          "point_pct": 53.59,
          "lower_pct": 51.08,
          "upper_pct": 56.07,
          "wins": 822,
          "n": 1534
        }
      },
      "best_wilson": {
        "point_pct": 40.38,
        "lower_pct": 28.16,
        "upper_pct": 53.93,
        "wins": 21,
        "n": 52
      },
      "primary_window": "5d",
      "primary_floor_pct": 51.0,
      "mode": "standard",
      "expected_value_pp": -6.667,
      "wilson_lower_pct": 28.16,
      "lifetime_significant": false,
      "regime_ok": true,
      "lifetime_ok": true,
      "ev_positive": false,
      "calibrated_ok": true
    },
    "wilson_lifetime_floor_pct": 51,
    "wilson_regime_floor_pct": 45
  }
}